continunet/__init__.py
continunet/constants.py
continunet/finder.py
continunet/image/__init__.py
continunet/image/fits.py
continunet/image/processing.py
continunet/network/__init__.py
continunet/network/trained_model.h5
continunet/network/unet.py
continunet-0.0.9.dist-info/LICENSE
continunet-0.0.9.dist-info/METADATA
continunet-0.0.9.dist-info/WHEEL
continunet-0.0.9.dist-info/top_level.txt
continunet-0.0.9.dist-info/RECORD
